LICENSE
xahau/__init__.py
xahau/account/__init__.py
xahau/account/main.py
xahau/account/py.typed
xahau/account/transaction_history.py
xahau/asyncio/__init__.py
xahau/asyncio/account/__init__.py
xahau/asyncio/account/main.py
xahau/asyncio/account/py.typed
xahau/asyncio/account/transaction_history.py
xahau/asyncio/clients/__init__.py
xahau/asyncio/clients/async_client.py
xahau/asyncio/clients/async_json_rpc_client.py
xahau/asyncio/clients/async_websocket_client.py
xahau/asyncio/clients/client.py
xahau/asyncio/clients/exceptions.py
xahau/asyncio/clients/json_rpc_base.py
xahau/asyncio/clients/py.typed
xahau/asyncio/clients/utils.py
xahau/asyncio/clients/websocket_base.py
xahau/asyncio/ledger/__init__.py
xahau/asyncio/ledger/main.py
xahau/asyncio/ledger/py.typed
xahau/asyncio/ledger/utils.py
xahau/asyncio/py.typed
xahau/asyncio/transaction/__init__.py
xahau/asyncio/transaction/main.py
xahau/asyncio/transaction/py.typed
xahau/asyncio/transaction/reliable_submission.py
xahau/asyncio/wallet/__init__.py
xahau/asyncio/wallet/py.typed
xahau/asyncio/wallet/wallet_generation.py
xahau/clients/__init__.py
xahau/clients/json_rpc_client.py
xahau/clients/py.typed
xahau/clients/sync_client.py
xahau/clients/websocket_client.py
xahau/constants.py
xahau/core/__init__.py
xahau/core/addresscodec/__init__.py
xahau/core/addresscodec/codec.py
xahau/core/addresscodec/exceptions.py
xahau/core/addresscodec/main.py
xahau/core/addresscodec/py.typed
xahau/core/addresscodec/utils.py
xahau/core/binarycodec/__init__.py
xahau/core/binarycodec/binary_wrappers/__init__.py
xahau/core/binarycodec/binary_wrappers/binary_parser.py
xahau/core/binarycodec/binary_wrappers/binary_serializer.py
xahau/core/binarycodec/definitions/__init__.py
xahau/core/binarycodec/definitions/definitions.json
xahau/core/binarycodec/definitions/definitions.py
xahau/core/binarycodec/definitions/field_header.py
xahau/core/binarycodec/definitions/field_info.py
xahau/core/binarycodec/definitions/field_instance.py
xahau_py-3.0.0.dist-info/LICENSE
xahau_py-3.0.0.dist-info/METADATA
xahau_py-3.0.0.dist-info/WHEEL
xahau_py-3.0.0.dist-info/RECORD
