Metadata-Version: 2.1
Name: xahau-py
Version: 3.0.0
Summary: A complete Python library for interacting with the Xahau Ledger
Home-page: https://github.com/Xahau/xahau-py
License: ISC
Keywords: xah,xahau,cryptocurrency
Author: Mayukha Vadari
Author-email: mvadari@ripple.com
Requires-Python: >=3.8,<4.0
Classifier: License :: OSI Approved
Classifier: Programming Language :: Python :: 3
Classifier: Programming Language :: Python :: 3.8
Classifier: Programming Language :: Python :: 3.9
Classifier: Programming Language :: Python :: 3.10
Classifier: Programming Language :: Python :: 3.11
Classifier: Programming Language :: Python :: 3.12
Requires-Dist: Deprecated (>=1.2.13,<2.0.0)
Requires-Dist: ECPy (>=1.2.5,<2.0.0)
Requires-Dist: base58 (>=2.1.0,<3.0.0)
Requires-Dist: httpx (>=0.18.1,<0.28.0)
Requires-Dist: pycryptodome (>=3.16.0,<4.0.0)
Requires-Dist: types-Deprecated (>=1.2.9,<2.0.0)
Requires-Dist: typing-extensions (>=4.2.0,<5.0.0)
Requires-Dist: websockets (>=11.0,<12.0)
Project-URL: Documentation, https://xahau-py.readthedocs.io
Project-URL: Repository, https://github.com/Xahau/xahau-py
